netbox_work_logs/__init__.py
netbox_work_logs/admin.py
netbox_work_logs/choices.py
netbox_work_logs/filters.py
netbox_work_logs/forms.py
netbox_work_logs/models.py
netbox_work_logs/tables.py
netbox_work_logs/template_content.py
netbox_work_logs/urls.py
netbox_work_logs/views.py
netbox_work_logs/api/serializers.py
netbox_work_logs/api/urls.py
netbox_work_logs/api/views.py
netbox_work_logs/doc/deviceworklog.md
netbox_work_logs/doc/vmworklog.md
netbox_work_logs/templates/netbox_work_logs/device/latest_logs.html
netbox_work_logs/templates/netbox_work_logs/device/inc/logs.html
netbox_work_logs/templates/netbox_work_logs/device/inc/logslist_btn.html
netbox_work_logs/templates/netbox_work_logs/device/worklog/worklog_detail.html
netbox_work_logs/templates/netbox_work_logs/device/worklog/worklog_edit.html
netbox_work_logs/templates/netbox_work_logs/device/worklog/worklog_list.html
netbox_work_logs/templates/netbox_work_logs/vm/latest_logs.html
netbox_work_logs/templates/netbox_work_logs/vm/inc/logs.html
netbox_work_logs/templates/netbox_work_logs/vm/inc/logslist_btn.html
netbox_work_logs/templates/netbox_work_logs/vm/worklog/worklog_detail.html
netbox_work_logs/templates/netbox_work_logs/vm/worklog/worklog_edit.html
netbox_work_logs/templates/netbox_work_logs/vm/worklog/worklog_list.html
netbox_work_logs-1.2.9.dist-info/METADATA
netbox_work_logs-1.2.9.dist-info/WHEEL
netbox_work_logs-1.2.9.dist-info/top_level.txt
netbox_work_logs-1.2.9.dist-info/RECORD
