Metadata-Version: 2.1
Name: netbox-work-logs
Version: 1.2.9
Summary: A NetBox work logs plugin
Home-page: https://github.com/vas-git/netbox-work-logs
Author: Vasilatos Vitaliy
License: Apache 2.0
Platform: UNKNOWN
